{"name": "Claremont, California Regional Tournament", "host": "Pomona College", "location": "Claremont, California", "start_date": "February 09, 2019", "end_date": "February 10, 2019", "level": "regionals", "year": "2019", "bid_start_date": "March 09, 2019", "bid_end_date": "March 10, 2019", "bid_location": "Los Angeles, California", "amta_rep_0": "Robson Hauser", "amta_rep_1": "Jacelyn Olson", "tab_note_0": "10th place after round 3: 4 Wins", "tab_note_1": "Opening coin flip: Tails - Lower # = Better Rank", "tab_note_2": "Round 3 coin flip: Tails - Left Side is Defense"}